llama_index/ingestion/ray/__init__.py
llama_index/ingestion/ray/base.py
llama_index/ingestion/ray/transform.py
llama_index/ingestion/ray/utils.py
llama_index_ingestion_ray-0.1.0.dist-info/METADATA
llama_index_ingestion_ray-0.1.0.dist-info/WHEEL
llama_index_ingestion_ray-0.1.0.dist-info/licenses/LICENSE
llama_index_ingestion_ray-0.1.0.dist-info/RECORD
