Metadata-Version: 2.4
Name: llama-index-ingestion-ray
Version: 0.1.0
Summary: llama-index Ray ingestion pipeline
Author-email: Florian Bacho <f.bacho@outlook.fr>
License-Expression: MIT
License-File: LICENSE
Requires-Python: <4.0,>=3.9
Requires-Dist: llama-index-core<0.15,>=0.13.0
Requires-Dist: ray[data]>=2.53.0
